feature_aggregation/__init__.py
feature_aggregation/base.py
feature_aggregation/bow.py
feature_aggregation/fv.py
feature_aggregation/llc.py
feature_aggregation/vlad.py
feature_aggregation-0.3.dist-info/DESCRIPTION.rst
feature_aggregation-0.3.dist-info/METADATA
feature_aggregation-0.3.dist-info/RECORD
feature_aggregation-0.3.dist-info/WHEEL
feature_aggregation-0.3.dist-info/metadata.json
feature_aggregation-0.3.dist-info/top_level.txt
