Metadata-Version: 2.0
Name: feature-aggregation
Version: 0.3
Summary: Aggregate local features into global features
Home-page: UNKNOWN
Author: Despoina Paschalidou <paschalidoud@gmail.com>, Angelos Katharopoulos <katharas@gmail.com>
Author-email: paschalidoud@gmail.com
License: MIT
Platform: UNKNOWN
Classifier: Intended Audience :: Science/Research
Classifier: Intended Audience :: Developers
Classifier: License :: OSI Approved :: MIT License
Classifier: Topic :: Scientific/Engineering
Classifier: Programming Language :: Python
Classifier: Programming Language :: Python :: 2
Classifier: Programming Language :: Python :: 2.7
Classifier: Programming Language :: Python :: 3
Classifier: Programming Language :: Python :: 3.4
Classifier: Programming Language :: Python :: 3.5
Requires-Dist: scikit-learn
